counter.v
module counter (
    input  wire       clk,
    input  wire       reset,
    output reg [3:0]  count
);

always @(posedge clk) begin
    if (reset)
        count <= 4'b0000;
    else
        count <= count + 1'b1;
end

endmodule

counter_tb.v
`timescale 1ns/1ps

module counter_tb;

    reg clk;
    reg reset;
    wire [3:0] count;

    // Notre FPGA
    counter dut (
        .clk(clk),
        .reset(reset),
        .count(count)
    );

    // Horloge : période de 10 ns
    always #5 clk = ~clk;

    initial begin

        // Enregistrer les signaux pour Surfer
        $dumpfile("counter.vcd");
        $dumpvars(0, counter_tb);

        // État initial
        clk   = 0;
        reset = 1;

        // Maintenir le reset pendant 20 ns
        #20;

        // Libérer le compteur
        reset = 0;

        // Laisser tourner pendant 160 ns
        #160;

        $finish;
    end

endmodule

counter.vcd
$date
	Tue Sep 15 14:12:32 2026
$end
$version
	Icarus Verilog
$end
$timescale
	1ps
$end
$scope module counter_tb $end
$var wire 4 ! count [3:0] $end
$var reg 1 " clk $end
$var reg 1 # reset $end
$scope module dut $end
$var wire 1 " clk $end
$var wire 1 # reset $end
$var reg 4 $ count [3:0] $end
$upscope $end
$upscope $end
$enddefinitions $end
$comment Show the parameter values. $end
$dumpall
$end
#0
$dumpvars
bx $
1#
0"
bx !
$end
#5000
b0 !
b0 $
1"
#10000
0"
#15000
1"
#20000
0"
0#
#25000
b1 !
b1 $
1"
#30000
0"
#35000
b10 !
b10 $
1"
#40000
0"
#45000
b11 !
b11 $
1"
#50000
0"
#55000
b100 !
b100 $
1"
#60000
0"
#65000
b101 !
b101 $
1"
#70000
0"
#75000
b110 !
b110 $
1"
#80000
0"
#85000
b111 !
b111 $
1"
#90000
0"
#95000
b1000 !
b1000 $
1"
#100000
0"
#105000
b1001 !
b1001 $
1"
#110000
0"
#115000
b1010 !
b1010 $
1"
#120000
0"
#125000
b1011 !
b1011 $
1"
#130000
0"
#135000
b1100 !
b1100 $
1"
#140000
0"
#145000
b1101 !
b1101 $
1"
#150000
0"
#155000
b1110 !
b1110 $
1"
#160000
0"
#165000
b1111 !
b1111 $
1"
#170000
0"
#175000
b0 !
b0 $
1"
